{
  "social_media": [
    {
      "channel": "Facebook",
      "followers": 1987,
      "likes": 400,
      "page_views": 52,
      "followers_change": 24,
      "page_views_change": 3,
      "likes_change": 2,
      "key": 1
    },
    {
      "channel": "Twitter",
      "followers": 1044,
      "likes": 507,
      "retweets": 117,
      "followers_change": 96,
      "retweets_change": 2,
      "likes_change": -6,
      "key": 2
    },
    {
      "channel": "Instagram",
      "followers": 11000,
      "likes": 107,
      "page_views": 52000,
      "followers_change": 214,
      "page_views_change": -7,
      "likes_change": 14,
      "key": 3
    },
    {
      "channel": "YouTube",
      "subscribers": 8239,
      "likes": 97,
      "page_views": 1407,
      "subscribers_change": -71,
      "page_views_change": -11,
      "likes_change": -2,
      "key": 4
    }
  ]
}